Melody_CLI.py
Melody_CLI-0.0.2.dist-info/LICENSE
Melody_CLI-0.0.2.dist-info/METADATA
Melody_CLI-0.0.2.dist-info/WHEEL
Melody_CLI-0.0.2.dist-info/top_level.txt
Melody_CLI-0.0.2.dist-info/RECORD
