Metadata-Version: 2.1
Name: Melody_CLI
Version: 0.0.2
Summary: A command-line music player that downloads and plays music from YouTube.
Home-page: https://github.com/pythonicforge/melody.CLI
Author: Hardik Jaiswal
Keywords: music player python,music player cli,melody-cli
Classifier: Programming Language :: Python :: 3
Classifier: License :: OSI Approved :: MIT License
Classifier: Operating System :: OS Independent
Requires-Python: >=3.10
License-File: LICENSE
Requires-Dist: pygame
Requires-Dist: yt-dlp
Requires-Dist: ytmusicapi
